hur/__init__.py
hur/hur.py
hur-1.1.4.dist-info/LICENSE.txt
hur-1.1.4.dist-info/METADATA
hur-1.1.4.dist-info/WHEEL
hur-1.1.4.dist-info/top_level.txt
hur-1.1.4.dist-info/RECORD
