Metadata-Version: 2.2
Name: hur
Version: 1.1.4
Home-page: https://github.com/sapiens-technology/Hur-Model
Author: SAPIENS TECHNOLOGY
License: Proprietary Software
License-File: LICENSE.txt
Requires-Dist: hurnet-torch
Requires-Dist: sapiens-tokenizer
Requires-Dist: sapiens-embedding
Requires-Dist: sapiens-attention
Requires-Dist: sapiens-infinite-context-window
Requires-Dist: sapiens-generalization
Requires-Dist: scn
Requires-Dist: torch
Requires-Dist: requests
Requires-Dist: ijson
Requires-Dist: tqdm
Dynamic: author
Dynamic: home-page
Dynamic: license
Dynamic: requires-dist
